onionizer/__about__.py
onionizer/__init__.py
onionizer/onionizer.py
onionizer/onionizer.py.html
onionizer-0.5.0.dist-info/METADATA
onionizer-0.5.0.dist-info/WHEEL
onionizer-0.5.0.dist-info/RECORD
