Metadata-Version: 2.1
Name: onionizer
Version: 0.5.0
Summary: A Python package to add middlewares to any function
Project-URL: Source code, https://github.com/brumar/onionizer
Author-email: bruno <martin.bruno.mail@gmail.com>
License: MIT
Keywords: decorator,middleware
Classifier: Development Status :: 4 - Beta
Classifier: Programming Language :: Python
Classifier: Programming Language :: Python :: 3.7
Classifier: Programming Language :: Python :: 3.8
Classifier: Programming Language :: Python :: 3.9
Classifier: Programming Language :: Python :: 3.10
Classifier: Programming Language :: Python :: 3.11
Classifier: Programming Language :: Python :: Implementation :: CPython
Provides-Extra: dev
Requires-Dist: black; extra == 'dev'
Requires-Dist: mkdocs==1.4.2; extra == 'dev'
Requires-Dist: pre-commit; extra == 'dev'
Requires-Dist: ruff==0.0.260; extra == 'dev'
